_stk.cpython-35m-x86_64-linux-gnu.so
libz.so
libz.so.1.2.11
_pydeform.cpython-35m-x86_64-linux-gnu.so
libz.so.1
.libslibz/libgomp-3300acd3.so.1.0.0
pydeform/interruptible.py
pydeform/sitk_api.py
pydeform/__init__.py
pydeform-0.5.1.dist-info/top_level.txt
pydeform-0.5.1.dist-info/RECORD
pydeform-0.5.1.dist-info/METADATA
pydeform-0.5.1.dist-info/WHEEL
.libs_stk/libgomp-3300acd3.so.1.0.0
.libs_pydeform/libgomp-3300acd3.so.1.0.0
