Metadata-Version: 2.1
Name: pydeform
Version: 0.5.1
Summary: UNKNOWN
Home-page: UNKNOWN
Author: Simon Ekström
Author-email: 
License: UNKNOWN
Platform: UNKNOWN
Requires-Dist: python-stk
Requires-Dist: numpy
Requires-Dist: PyYAML
